azure/mgmt/peering/__init__.py
azure/mgmt/peering/_configuration.py
azure/mgmt/peering/_peering_management_client.py
azure/mgmt/peering/_version.py
azure/mgmt/peering/aio/__init__.py
azure/mgmt/peering/aio/_configuration.py
azure/mgmt/peering/aio/_peering_management_client.py
azure/mgmt/peering/aio/operations/__init__.py
azure/mgmt/peering/aio/operations/_legacy_peerings_operations.py
azure/mgmt/peering/aio/operations/_operations.py
azure/mgmt/peering/aio/operations/_peer_asns_operations.py
azure/mgmt/peering/aio/operations/_peering_locations_operations.py
azure/mgmt/peering/aio/operations/_peering_management_client_operations.py
azure/mgmt/peering/aio/operations/_peering_service_locations_operations.py
azure/mgmt/peering/aio/operations/_peering_service_prefixes_operations.py
azure/mgmt/peering/aio/operations/_peering_service_providers_operations.py
azure/mgmt/peering/aio/operations/_peering_services_operations.py
azure/mgmt/peering/aio/operations/_peerings_operations.py
azure/mgmt/peering/aio/operations/_prefixes_operations.py
azure/mgmt/peering/models/__init__.py
azure/mgmt/peering/models/_models.py
azure/mgmt/peering/models/_models_py3.py
azure/mgmt/peering/models/_peering_management_client_enums.py
azure/mgmt/peering/operations/__init__.py
azure/mgmt/peering/operations/_legacy_peerings_operations.py
azure/mgmt/peering/operations/_operations.py
azure/mgmt/peering/operations/_peer_asns_operations.py
azure/mgmt/peering/operations/_peering_locations_operations.py
azure/mgmt/peering/operations/_peering_management_client_operations.py
azure/mgmt/peering/operations/_peering_service_locations_operations.py
azure/mgmt/peering/operations/_peering_service_prefixes_operations.py
azure/mgmt/peering/operations/_peering_service_providers_operations.py
azure/mgmt/peering/operations/_peering_services_operations.py
azure/mgmt/peering/operations/_peerings_operations.py
azure/mgmt/peering/operations/_prefixes_operations.py
azure_mgmt_peering-1.0.0.dist-info/METADATA
azure_mgmt_peering-1.0.0.dist-info/WHEEL
azure_mgmt_peering-1.0.0.dist-info/top_level.txt
azure_mgmt_peering-1.0.0.dist-info/RECORD
